config.py
dissector.py
main.py
model.py
utils.py
handmark-0.5.2.1.dist-info/licenses/LICENSE
models/__init__.py
models/base.py
models/json.py
models/markdown.py
models/xml.py
models/yaml.py
providers/__init__.py
providers/azure_provider.py
providers/base.py
providers/factory.py
providers/ollama_provider.py
handmark-0.5.2.1.dist-info/METADATA
handmark-0.5.2.1.dist-info/WHEEL
handmark-0.5.2.1.dist-info/entry_points.txt
handmark-0.5.2.1.dist-info/top_level.txt
handmark-0.5.2.1.dist-info/RECORD
