Metadata-Version: 2.4
Name: handmark
Version: 0.5.2.1
Summary: Transform handwritten images into structured documents (Markdown, JSON, YAML, XML)
Author-email: Gabriel Borges <dev.gabrielsborges@proton.me>
Project-URL: Homepage, https://github.com/devgabrielsborges/handmark
Project-URL: Bug Tracker, https://github.com/devgabrielsborges/handmark/issues
Requires-Python: >=3.10
License-File: LICENSE
Requires-Dist: azure-ai-inference>=1.0.0b9
Requires-Dist: python-dotenv>=1.1.0
Requires-Dist: requests>=2.32.3
Requires-Dist: pytest
Requires-Dist: pytest-mock
Requires-Dist: typer>=0.15.4
Requires-Dist: rich>=14.0.0
Requires-Dist: pyyaml>=6.0
Requires-Dist: lxml>=4.9.0
Requires-Dist: ollama>=0.1.0
Dynamic: license-file
